[
    {
        "_id": "5d725a4a7b292f5f8cefg600",
        "event": "5d725a4a7b292f5f8ceff787",
        "name": "Royal Highland Center Venue",
        "ageRestrictions": "AGE_RESTRICTION_MIN_SIXTEEN",
        "venueCapacity": 10500,
        "address": "Ingliston, Newbridge EH28 8NB"
    },

    {
        "_id": "5d725a4a7b292f5f8cefg601",
        "event": "5d725a4a7b292f5f8ceff788",
        "name": "Three Sisters Cowgate Venue",
        "ageRestrictions": "AGE_RESTRICTION_MIN_EIGHTEEN",
        "venueCapacity": 150,
        "address": "139 Cowgate, Edinburgh EH1 1JS"
    }






]